mamonsu/__init__.py
mamonsu/lib/__init__.py
mamonsu/lib/config.py
mamonsu/lib/const.py
mamonsu/lib/default_config.py
mamonsu/lib/get_keys.py
mamonsu/lib/parser.py
mamonsu/lib/platform.py
mamonsu/lib/plugin.py
mamonsu/lib/queue.py
mamonsu/lib/runner.py
mamonsu/lib/sender.py
mamonsu/lib/supervisor.py
mamonsu/lib/zbx_template.py
mamonsu/lib/senders/__init__.py
mamonsu/lib/senders/log.py
mamonsu/lib/senders/zbx.py
mamonsu/plugins/__init__.py
mamonsu/plugins/common/__init__.py
mamonsu/plugins/common/health.py
mamonsu/plugins/pgsql/__init__.py
mamonsu/plugins/pgsql/archive_command.py
mamonsu/plugins/pgsql/bgwriter.py
mamonsu/plugins/pgsql/cfs.py
mamonsu/plugins/pgsql/checkpoint.py
mamonsu/plugins/pgsql/connections.py
mamonsu/plugins/pgsql/databases.py
mamonsu/plugins/pgsql/health.py
mamonsu/plugins/pgsql/instance.py
mamonsu/plugins/pgsql/oldest.py
mamonsu/plugins/pgsql/pg_buffercache.py
mamonsu/plugins/pgsql/pg_locks.py
mamonsu/plugins/pgsql/pg_stat_statement.py
mamonsu/plugins/pgsql/pg_wait_sampling.py
mamonsu/plugins/pgsql/plugin.py
mamonsu/plugins/pgsql/pool.py
mamonsu/plugins/pgsql/xlog.py
mamonsu/plugins/pgsql/driver/__init__.py
mamonsu/plugins/pgsql/driver/checks.py
mamonsu/plugins/pgsql/driver/connection.py
mamonsu/plugins/pgsql/driver/pool.py
mamonsu/plugins/pgsql/driver/pg8000/__init__.py
mamonsu/plugins/pgsql/driver/pg8000/core.py
mamonsu/plugins/pgsql/driver/pg8000/six.py
mamonsu/plugins/system/__init__.py
mamonsu/plugins/system/plugin.py
mamonsu/plugins/system/linux/__init__.py
mamonsu/plugins/system/linux/disk_sizes.py
mamonsu/plugins/system/linux/disk_stats.py
mamonsu/plugins/system/linux/la.py
mamonsu/plugins/system/linux/memory.py
mamonsu/plugins/system/linux/net.py
mamonsu/plugins/system/linux/open_files.py
mamonsu/plugins/system/linux/proc_stat.py
mamonsu/plugins/system/linux/scripts.py
mamonsu/plugins/system/linux/uptime.py
mamonsu/plugins/system/windows/__init__.py
mamonsu/plugins/system/windows/cpu.py
mamonsu/plugins/system/windows/disk_stats.py
mamonsu-2.4.1.dist-info/LICENSE
mamonsu-2.4.1.dist-info/METADATA
mamonsu-2.4.1.dist-info/WHEEL
mamonsu-2.4.1.dist-info/entry_points.txt
mamonsu-2.4.1.dist-info/top_level.txt
mamonsu-2.4.1.dist-info/zip-safe
mamonsu-2.4.1.dist-info/RECORD
