Metadata-Version: 2.1
Name: mamonsu
Version: 2.4.1
Summary: Monitoring agent for PostgreSQL
Home-page: https://github.com/postgrespro/mamonsu
Author: Dmitry Vasilyev
Author-email: info@postgrespro.ru
License: BSD
Keywords: monitoring,zabbix,postgres
Platform: UNKNOWN
Classifier: Environment :: Console
Classifier: Intended Audience :: System Administrators
Classifier: Operating System :: POSIX :: Linux
Classifier: Operating System :: Microsoft :: Windows
Classifier: License :: OSI Approved :: BSD License
Classifier: Programming Language :: Python :: 2
Classifier: Programming Language :: Python :: 3
Classifier: Topic :: System :: Monitoring
